MODELS/__init__.py
MODELS/candles.py
MODELS/overnight.py
UTILS/MACD_SYNTHESIS.py
UTILS/__init__.py
UTILS/charting.py
UTILS/check_recent.py
UTILS/confluence.py
UTILS/db_run.py
UTILS/db_schema.py
UTILS/db_tables.py
UTILS/exposure.py
UTILS/helpers.py
UTILS/imps.py
UTILS/query_dict.py
UTILS/table_queries.py
UTILS/ticker_dicts.py
UTILS/verify_db.py
_webull/__init__.py
_webull/helpers.py
_webull/models/__init__.py
_webull/models/alerts.py
_webull/models/capital_flow.py
_webull/models/dividends.py
_webull/models/etf_holdings.py
_webull/models/financials.py
_webull/models/instutitions.py
_webull/models/ipos.py
_webull/models/most_active.py
_webull/models/overnight.py
_webull/models/paper_trade.py
_webull/models/rise_fall.py
_webull/models/technical_events.py
_webull/models/ticker_bonds.py
_webull/models/top_followed.py
_yfinance/__init__.py
_yfinance/models/__init__.py
_yfinance/models/news.py
_yfinance/models/price_target.py
feeds/__init__.py
feeds/rsi_td9_bbands.py
feeds/rsi_td9_bbands_bear.py
feeds/rsi_td9_bbands_rvol.py
feeds/rsi_td9_bbands_rvol_bear.py
feeds/rule_factory_feeds.py
feeds/top_bearish_feed.py
feeds/top_bullish_feed.py
feeds/top_reversal_feeds.py
fudstop4/__init__.py
fudstop4/all_helpers.py
fudstop4/plots.py
fudstop4/schema.py
fudstop4/_markets/__init__.py
fudstop4/_markets/embeddings.py
fudstop4/_markets/webhook_dicts.py
fudstop4/_markets/list_sets/__init__.py
fudstop4/_markets/list_sets/dicts.py
fudstop4/_markets/list_sets/saved_tickers.py
fudstop4/_markets/list_sets/ticker_lists.py
fudstop4/_markets/list_sets/webhook_dicts.py
fudstop4/_markets/market_handlers/__init__.py
fudstop4/_markets/market_handlers/cfg.py
fudstop4/_markets/market_handlers/crypto.py
fudstop4/_markets/market_handlers/database_.py
fudstop4/_markets/market_handlers/forex.py
fudstop4/_markets/market_handlers/indices.py
fudstop4/_markets/market_handlers/list_sets.py
fudstop4/_markets/market_handlers/options.py
fudstop4/_markets/market_handlers/stocks.py
fudstop4/apis/__init__.py
fudstop4-1.5.0.dist-info/METADATA
fudstop4-1.5.0.dist-info/WHEEL
fudstop4-1.5.0.dist-info/top_level.txt
fudstop4-1.5.0.dist-info/RECORD
